fb_library/__init__.py
fb_library/antichamfer.py
fb_library/ball_socket.py
fb_library/basic_shapes.py
fb_library/bolt_fittings.py
fb_library/click_fit.py
fb_library/dovetail.py
fb_library/hexwall.py
fb_library/high_top_slide_box.py
fb_library/point.py
fb_library/slide_box.py
fb_library/twist_snap.py
fb_library-0.0.41.dist-info/METADATA
fb_library-0.0.41.dist-info/WHEEL
fb_library-0.0.41.dist-info/licenses/LICENSE
fb_library-0.0.41.dist-info/RECORD
