Metadata-Version: 2.4
Name: fb-library
Version: 0.0.41
Summary: build123d libraries and utilities
Project-URL: Homepage, https://github.com/x0pherl/fb-library
Project-URL: Issues, https://github.com/x0pherl/fb-library/issues
Project-URL: Documentation, https://fb-library.readthedocs.org
Author: x0pherl
License-File: LICENSE
Classifier: License :: OSI Approved :: MIT License
Classifier: Operating System :: OS Independent
Classifier: Programming Language :: Python :: 3
Requires-Python: >=3.8
